tests/__init__.py
tests/conftest.py
tests/test_common.py
tests/test_controller.py
tests/test_date_checker.py
tests/test_image_service.py
tests/test_object_mapper.py
tests/test_search_service.py
tests/test_text_service.py
tests/test_uploader.py
tests/test_validator.py
tests/test_verification_accuracy.py
verifytweet/__init__.py
verifytweet/app.py
verifytweet/cli.py
verifytweet/config/__init__.py
verifytweet/config/settings.py
verifytweet/services/__init__.py
verifytweet/services/controller.py
verifytweet/services/image.py
verifytweet/services/search.py
verifytweet/services/text.py
verifytweet/util/__init__.py
verifytweet/util/common.py
verifytweet/util/date_checker.py
verifytweet/util/logging.py
verifytweet/util/object_mapper.py
verifytweet/util/result.py
verifytweet/util/uploader.py
verifytweet/util/validator.py
verifytweet-0.6.0.dist-info/LICENSE
verifytweet-0.6.0.dist-info/METADATA
verifytweet-0.6.0.dist-info/WHEEL
verifytweet-0.6.0.dist-info/entry_points.txt
verifytweet-0.6.0.dist-info/top_level.txt
verifytweet-0.6.0.dist-info/RECORD
