Metadata-Version: 2.1
Name: verifytweet
Version: 0.6.0
Summary: A tool to verify Tweet screenshots
Home-page: https://preethamkamidi.com/projects/verify
Author: Preetham Kamidi
Author-email: contact@preethamkamidi.com
License: AGPLv3
Project-URL: Documentation, https://github.com/kamidipreetham/verifytweet
Project-URL: Code, https://github.com/kamidipreetham/verifytweet
Project-URL: Issue tracker, https://github.com/kamidipreetham/verifytweet/issues
Platform: UNKNOWN
Classifier: Development Status :: 3 - Alpha
Classifier: Environment :: Console
Classifier: Intended Audience :: Information Technology
Classifier: License :: OSI Approved :: GNU Affero General Public License v3
Classifier: Operating System :: OS Independent
Classifier: Programming Language :: Python
Classifier: Programming Language :: Python :: 3
Classifier: Programming Language :: Python :: 3.6
Classifier: Programming Language :: Python :: 3.7
Requires-Python: >=3.6.*
Requires-Dist: click (>=5.1)
Requires-Dist: Pillow (>=6.2.0)
Requires-Dist: pytesseract (==0.2.6)
Requires-Dist: requests (==2.22.0)
Requires-Dist: scikit-learn (==0.21.2)
Requires-Dist: nltk (>=3.4.5)
Requires-Dist: python-dateutil (==2.8.0)
Requires-Dist: werkzeug (==0.15.4)
Requires-Dist: twint (==2.1.13)
